timeordered_pagination
