Metadata-Version: 1.1
Name: drf-timeordered-pagination
Version: 0.1.1
Summary: Utility classes to provide time-ordered pagination over 
Home-page: https://github.com/andrewdodd/drf-timeordered-pagination
Author: Andrew Dodd
Author-email: andrew.john.dodd@gmail.com
License: MIT
Keywords: Django Rest Framework,Django,Pagination
Platform: UNKNOWN
Classifier: Development Status :: 3 - Alpha
Classifier: Intended Audience :: Developers
Classifier: Natural Language :: English
Classifier: License :: Other/Proprietary License
Classifier: Operating System :: OS Independent
Classifier: Framework :: Django
Classifier: Framework :: Django :: 1.8
Classifier: Framework :: Django :: 1.9
Classifier: Intended Audience :: Developers
Classifier: Programming Language :: Python
Classifier: Programming Language :: Python :: 2
Classifier: Programming Language :: Python :: 2.7
Classifier: Programming Language :: Python :: 3
Classifier: Programming Language :: Python :: 3.4
Classifier: Programming Language :: Python :: 3.5
Classifier: Programming Language :: Python :: 3.6
Classifier: Topic :: Software Development :: Libraries :: Python Modules
